djangocms_slick_slider/__init__.py
djangocms_slick_slider/admin.py
djangocms_slick_slider/apps.py
djangocms_slick_slider/cms_plugins.py
djangocms_slick_slider/forms.py
djangocms_slick_slider/helpers.py
djangocms_slick_slider/models.py
djangocms_slick_slider/settings.py
djangocms_slick_slider/migrations/0001_initial.py
djangocms_slick_slider/migrations/0002_slicksliderimage_link_target.py
djangocms_slick_slider/migrations/0003_auto_20180201_2050.py
djangocms_slick_slider/migrations/0004_auto_20191202_1727.py
djangocms_slick_slider/migrations/__init__.py
djangocms_slick_slider/static/css/djangocms_slick_slider.css
djangocms_slick_slider/static/js/djangocms_slick_slider.js
djangocms_slick_slider/static/slick/ajax-loader.gif
djangocms_slick_slider/static/slick/slick-theme.css
djangocms_slick_slider/static/slick/slick.css
djangocms_slick_slider/static/slick/slick.js
djangocms_slick_slider/static/slick/slick.min.js
djangocms_slick_slider/static/slick/fonts/slick.eot
djangocms_slick_slider/static/slick/fonts/slick.svg
djangocms_slick_slider/static/slick/fonts/slick.ttf
djangocms_slick_slider/static/slick/fonts/slick.woff
djangocms_slick_slider/templates/djangocms_slick_slider/base.html
djangocms_slick_slider/templates/djangocms_slick_slider/change_form.html
djangocms_slick_slider/templatetags/__init__.py
djangocms_slick_slider/templatetags/djangocms_slick_slider_utils.py
djangocms_slick_slider-0.6.0.dist-info/DESCRIPTION.rst
djangocms_slick_slider-0.6.0.dist-info/METADATA
djangocms_slick_slider-0.6.0.dist-info/RECORD
djangocms_slick_slider-0.6.0.dist-info/WHEEL
djangocms_slick_slider-0.6.0.dist-info/metadata.json
djangocms_slick_slider-0.6.0.dist-info/top_level.txt
