Metadata-Version: 2.0
Name: djangocms-slick-slider
Version: 0.6.0
Summary: A Django CMS Slider Plugin with Slick
Home-page: https://github.com/oesah/djangocms_slick_slider
Author: Özer Sahin
Author-email: o.sahin@oesah.de
License: MIT
Keywords: djangocms-slick-slider
Platform: UNKNOWN
Classifier: Development Status :: 3 - Alpha
Classifier: Framework :: Django
Classifier: Framework :: Django :: 1.10
Classifier: Framework :: Django :: 1.11
Classifier: Intended Audience :: Developers
Classifier: License :: OSI Approved :: BSD License
Classifier: Natural Language :: English
Classifier: Programming Language :: Python :: 2.7
Classifier: Programming Language :: Python :: 3.5
Requires-Dist: django-cms (<3.5)
Requires-Dist: jsonfield (<2.1)
Requires-Dist: django-filer (<1.6.0)
